pyblinkers/__init__.py
pyblinkers/default_setting.py
pyblinkers/pyblinker.py
pyblinkers/utilities/__init__.py
pyblinkers/utilities/extractBlinkProperties.py
pyblinkers/utilities/fit_blink.py
pyblinkers/utilities/getCandidateSignal.py
pyblinkers/utilities/misc.py
pyblinkers/utilities/zero_crossing.py
pyblinkers/vislab/__init__.py
pyblinkers/vislab/base_left_right.py
pyblinkers/vislab/blink_posi_vislab.py
pyblinkers/vislab/getBlinkPositions_vislab.py
pyblinkers/viz/__init__.py
pyblinkers/viz/viz_pd.py
pyblinkers/viz/viz_sanity.py
pyblinkers-0.0.6.dist-info/METADATA
pyblinkers-0.0.6.dist-info/WHEEL
pyblinkers-0.0.6.dist-info/top_level.txt
pyblinkers-0.0.6.dist-info/RECORD
