Metadata-Version: 2.1
Name: pyblinkers
Version: 0.0.6
Summary: make life easier
Author: rpb
Requires-Dist: seaborn
